mir/monads/__init__.py
mir/monads/abc.py
mir/monads/base.py
mir/monads/data.py
mir/monads/fun.py
mir/monads/id.py
mir/monads/maybe.py
mir.monads-1.0.0.dist-info/DESCRIPTION.rst
mir.monads-1.0.0.dist-info/METADATA
mir.monads-1.0.0.dist-info/RECORD
mir.monads-1.0.0.dist-info/WHEEL
mir.monads-1.0.0.dist-info/metadata.json
mir.monads-1.0.0.dist-info/top_level.txt
