Metadata-Version: 2.0
Name: mir.monads
Version: 1.0.0
Summary: Monads for Python.
Home-page: https://github.com/darkfeline/mir.monads
Author: Allen Li
Author-email: darkfeline@felesatra.moe
License: UNKNOWN
Platform: UNKNOWN
Classifier: Development Status :: 5 - Production/Stable
Classifier: Intended Audience :: Developers
Classifier: License :: OSI Approved :: Apache Software License
Classifier: Programming Language :: Python :: 3.5
